microquest
