Metadata-Version: 1.0
Name: microquest
Version: 0.1.11
Summary: microquest - gamify anything - a cli alternative to liferpg / habitica
Home-page: http://github.com/trqx/microquest
Author: trqx
Author-email: trqx@goat.si
License: MIT
Platform: UNKNOWN
